wxcast/__init__.py
wxcast/api.py
wxcast/cli.py
wxcast/constants.py
wxcast/exceptions.py
wxcast/utils.py
wxcast-2.0.0.dist-info/LICENSE
wxcast-2.0.0.dist-info/METADATA
wxcast-2.0.0.dist-info/WHEEL
wxcast-2.0.0.dist-info/entry_points.txt
wxcast-2.0.0.dist-info/top_level.txt
wxcast-2.0.0.dist-info/RECORD
