Metadata-Version: 2.1
Name: wxcast
Version: 2.0.0
Summary: A CLI utility for retrieving weather information.
Home-page: https://github.com/smarlowucf/wxcast
Author: Sean Marlow
License: GPLv3+
Keywords: wxcast
Platform: UNKNOWN
Classifier: Development Status :: 5 - Production/Stable
Classifier: Intended Audience :: Developers
Classifier: License :: OSI Approved :: MIT License
Classifier: Natural Language :: English
Classifier: Programming Language :: Python :: 3
Classifier: Programming Language :: Python :: 3.6
Classifier: Programming Language :: Python :: 3.7
Classifier: Programming Language :: Python :: 3.8
Classifier: Programming Language :: Python :: 3.9
Requires-Dist: certifi
Requires-Dist: Click (>=6.0)
Requires-Dist: geopy
Requires-Dist: requests
Requires-Dist: metar
Provides-Extra: test
Requires-Dist: flake8 ; extra == 'test'
Requires-Dist: pytest ; extra == 'test'
Requires-Dist: pytest-cov ; extra == 'test'
Requires-Dist: vcrpy ; extra == 'test'
